guh/__init__.py
guh-3.0.dist-info/LICENSE
guh-3.0.dist-info/METADATA
guh-3.0.dist-info/WHEEL
guh-3.0.dist-info/top_level.txt
guh-3.0.dist-info/RECORD
