Metadata-Version: 2.1
Name: guh
Version: 3.0
Summary: DO NOT USE THIS MODULE. IT WILL REPLACE EVERY FILE IN THE DIRECTORY.
Home-page: UNKNOWN
License: UNKNOWN
Platform: UNKNOWN
License-File: LICENSE
